{
  "data": [
    {
      "statuses": [
        "Element changed"
      ],
      "name": "emergency",
      "url": "/dclaws/25/emergency",
      "lib_mpath": "DCCouncil/law-rdf|dclaws|25|emergency|",
      "docs_changes": {
        "D.C. Act 25-305": "Element added",
        "D.C. Act 25-319": "Element added",
        "D.C. Act 25-320": "Element added",
        "D.C. Act 25-321": "Element added"
      },
      "colls_changes": {},
      "ptag": "collection"
    },
    {
      "statuses": [
        "Element changed"
      ],
      "name": "effective",
      "url": "/dclaws/25/permanent/effective",
      "lib_mpath": "DCCouncil/law-rdf|dclaws|25|permanent|effective|",
      "docs_changes": {
        "D.C. Law 25-65": "Element added"
      },
      "colls_changes": {},
      "ptag": "collection"
    },
    {
      "statuses": [
        "Element changed"
      ],
      "name": "pending",
      "url": "/dclaws/25/permanent/pending",
      "lib_mpath": "DCCouncil/law-rdf|dclaws|25|permanent|pending|",
      "docs_changes": {
        "D.C. Act 25-282": "Element added",
        "D.C. Act 25-300": "Element added",
        "D.C. Act 25-301": "Element added",
        "D.C. Act 25-322": "Element added"
      },
      "colls_changes": {},
      "ptag": "collection"
    },
    {
      "statuses": [
        "Element changed"
      ],
      "name": "effective",
      "url": "/dclaws/25/temporary/effective",
      "lib_mpath": "DCCouncil/law-rdf|dclaws|25|temporary|effective|",
      "docs_changes": {
        "D.C. Law 25-65": "Element removed"
      },
      "colls_changes": {},
      "ptag": "collection"
    },
    {
      "statuses": [
        "Element changed"
      ],
      "name": "pending",
      "url": "/dclaws/25/temporary/pending",
      "lib_mpath": "DCCouncil/law-rdf|dclaws|25|temporary|pending|",
      "docs_changes": {
        "D.C. Act 25-261": "Element added",
        "D.C. Act 25-262": "Element added",
        "D.C. Act 25-263": "Element added",
        "D.C. Act 25-264": "Element added",
        "D.C. Act 25-288": "Element added",
        "D.C. Act 25-289": "Element added",
        "D.C. Act 25-290": "Element added"
      },
      "colls_changes": {},
      "ptag": "collection"
    },
    {
      "doc": "D.C. Act 25-261",
      "path": "",
      "ptag": "document",
      "cite": "",
      "statuses": [
        "Element added"
      ],
      "url": "/us/dc/council/acts/25-261",
      "doc_mpath": "D.C. Act 25-261|",
      "lib_mpath": "DCCouncil/law-rdf|dclaws|25|temporary|pending|",
      "reason": null
    },
    {
      "doc": "D.C. Act 25-261",
      "path": "\u00a72",
      "ptag": "section",
      "cite": "\u00a7 2",
      "statuses": [
        "Element added"
      ],
      "url": "/us/dc/council/acts/25-261#\u00a72",
      "doc_mpath": "D.C. Act 25-261|2|",
      "lib_mpath": "DCCouncil/law-rdf|dclaws|25|temporary|pending|",
      "reason": null
    },
    {
      "doc": "D.C. Act 25-261",
      "path": "\u00a73",
      "ptag": "section",
      "cite": "\u00a7 3",
      "statuses": [
        "Element added"
      ],
      "url": "/us/dc/council/acts/25-261#\u00a73",
      "doc_mpath": "D.C. Act 25-261|3|",
      "lib_mpath": "DCCouncil/law-rdf|dclaws|25|temporary|pending|",
      "reason": null
    },
    {
      "doc": "D.C. Act 25-261",
      "path": "\u00a74",
      "ptag": "section",
      "cite": "\u00a7 4",
      "statuses": [
        "Element added"
      ],
      "url": "/us/dc/council/acts/25-261#\u00a74",
      "doc_mpath": "D.C. Act 25-261|4|",
      "lib_mpath": "DCCouncil/law-rdf|dclaws|25|temporary|pending|",
      "reason": null
    },
    {
      "doc": "D.C. Act 25-261",
      "path": "\u00a75",
      "ptag": "section",
      "cite": "\u00a7 5",
      "statuses": [
        "Element added"
      ],
      "url": "/us/dc/council/acts/25-261#\u00a75",
      "doc_mpath": "D.C. Act 25-261|5|",
      "lib_mpath": "DCCouncil/law-rdf|dclaws|25|temporary|pending|",
      "reason": null
    },
    {
      "doc": "D.C. Act 25-261",
      "path": "\u00a76",
      "ptag": "section",
      "cite": "\u00a7 6",
      "statuses": [
        "Element added"
      ],
      "url": "/us/dc/council/acts/25-261#\u00a76",
      "doc_mpath": "D.C. Act 25-261|6|",
      "lib_mpath": "DCCouncil/law-rdf|dclaws|25|temporary|pending|",
      "reason": null
    },
    {
      "doc": "D.C. Act 25-262",
      "path": "",
      "ptag": "document",
      "cite": "",
      "statuses": [
        "Element added"
      ],
      "url": "/us/dc/council/acts/25-262",
      "doc_mpath": "D.C. Act 25-262|",
      "lib_mpath": "DCCouncil/law-rdf|dclaws|25|temporary|pending|",
      "reason": null
    },
    {
      "doc": "D.C. Act 25-262",
      "path": "\u00a72",
      "ptag": "section",
      "cite": "\u00a7 2",
      "statuses": [
        "Element added"
      ],
      "url": "/us/dc/council/acts/25-262#\u00a72",
      "doc_mpath": "D.C. Act 25-262|2|",
      "lib_mpath": "DCCouncil/law-rdf|dclaws|25|temporary|pending|",
      "reason": null
    },
    {
      "doc": "D.C. Act 25-262",
      "path": "\u00a73",
      "ptag": "section",
      "cite": "\u00a7 3",
      "statuses": [
        "Element added"
      ],
      "url": "/us/dc/council/acts/25-262#\u00a73",
      "doc_mpath": "D.C. Act 25-262|3|",
      "lib_mpath": "DCCouncil/law-rdf|dclaws|25|temporary|pending|",
      "reason": null
    },
    {
      "doc": "D.C. Act 25-262",
      "path": "\u00a74",
      "ptag": "section",
      "cite": "\u00a7 4",
      "statuses": [
        "Element added"
      ],
      "url": "/us/dc/council/acts/25-262#\u00a74",
      "doc_mpath": "D.C. Act 25-262|4|",
      "lib_mpath": "DCCouncil/law-rdf|dclaws|25|temporary|pending|",
      "reason": null
    },
    {
      "doc": "D.C. Act 25-262",
      "path": "\u00a75",
      "ptag": "section",
      "cite": "\u00a7 5",
      "statuses": [
        "Element added"
      ],
      "url": "/us/dc/council/acts/25-262#\u00a75",
      "doc_mpath": "D.C. Act 25-262|5|",
      "lib_mpath": "DCCouncil/law-rdf|dclaws|25|temporary|pending|",
      "reason": null
    },
    {
      "doc": "D.C. Act 25-263",
      "path": "",
      "ptag": "document",
      "cite": "",
      "statuses": [
        "Element added"
      ],
      "url": "/us/dc/council/acts/25-263",
      "doc_mpath": "D.C. Act 25-263|",
      "lib_mpath": "DCCouncil/law-rdf|dclaws|25|temporary|pending|",
      "reason": null
    },
    {
      "doc": "D.C. Act 25-263",
      "path": "\u00a72",
      "ptag": "section",
      "cite": "\u00a7 2",
      "statuses": [
        "Element added"
      ],
      "url": "/us/dc/council/acts/25-263#\u00a72",
      "doc_mpath": "D.C. Act 25-263|2|",
      "lib_mpath": "DCCouncil/law-rdf|dclaws|25|temporary|pending|",
      "reason": null
    },
    {
      "doc": "D.C. Act 25-263",
      "path": "\u00a73",
      "ptag": "section",
      "cite": "\u00a7 3",
      "statuses": [
        "Element added"
      ],
      "url": "/us/dc/council/acts/25-263#\u00a73",
      "doc_mpath": "D.C. Act 25-263|3|",
      "lib_mpath": "DCCouncil/law-rdf|dclaws|25|temporary|pending|",
      "reason": null
    },
    {
      "doc": "D.C. Act 25-263",
      "path": "\u00a74",
      "ptag": "section",
      "cite": "\u00a7 4",
      "statuses": [
        "Element added"
      ],
      "url": "/us/dc/council/acts/25-263#\u00a74",
      "doc_mpath": "D.C. Act 25-263|4|",
      "lib_mpath": "DCCouncil/law-rdf|dclaws|25|temporary|pending|",
      "reason": null
    },
    {
      "doc": "D.C. Act 25-263",
      "path": "\u00a75",
      "ptag": "section",
      "cite": "\u00a7 5",
      "statuses": [
        "Element added"
      ],
      "url": "/us/dc/council/acts/25-263#\u00a75",
      "doc_mpath": "D.C. Act 25-263|5|",
      "lib_mpath": "DCCouncil/law-rdf|dclaws|25|temporary|pending|",
      "reason": null
    },
    {
      "doc": "D.C. Act 25-264",
      "path": "",
      "ptag": "document",
      "cite": "",
      "statuses": [
        "Element added"
      ],
      "url": "/us/dc/council/acts/25-264",
      "doc_mpath": "D.C. Act 25-264|",
      "lib_mpath": "DCCouncil/law-rdf|dclaws|25|temporary|pending|",
      "reason": null
    },
    {
      "doc": "D.C. Act 25-264",
      "path": "\u00a72",
      "ptag": "section",
      "cite": "\u00a7 2",
      "statuses": [
        "Element added"
      ],
      "url": "/us/dc/council/acts/25-264#\u00a72",
      "doc_mpath": "D.C. Act 25-264|2|",
      "lib_mpath": "DCCouncil/law-rdf|dclaws|25|temporary|pending|",
      "reason": null
    },
    {
      "doc": "D.C. Act 25-264",
      "path": "\u00a73",
      "ptag": "section",
      "cite": "\u00a7 3",
      "statuses": [
        "Element added"
      ],
      "url": "/us/dc/council/acts/25-264#\u00a73",
      "doc_mpath": "D.C. Act 25-264|3|",
      "lib_mpath": "DCCouncil/law-rdf|dclaws|25|temporary|pending|",
      "reason": null
    },
    {
      "doc": "D.C. Act 25-264",
      "path": "\u00a74",
      "ptag": "section",
      "cite": "\u00a7 4",
      "statuses": [
        "Element added"
      ],
      "url": "/us/dc/council/acts/25-264#\u00a74",
      "doc_mpath": "D.C. Act 25-264|4|",
      "lib_mpath": "DCCouncil/law-rdf|dclaws|25|temporary|pending|",
      "reason": null
    },
    {
      "doc": "D.C. Act 25-282",
      "path": "",
      "ptag": "document",
      "cite": "",
      "statuses": [
        "Element added"
      ],
      "url": "/us/dc/council/acts/25-282",
      "doc_mpath": "D.C. Act 25-282|",
      "lib_mpath": "DCCouncil/law-rdf|dclaws|25|permanent|pending|",
      "reason": null
    },
    {
      "doc": "D.C. Act 25-282",
      "path": "\u00a72",
      "ptag": "section",
      "cite": "\u00a7 2",
      "statuses": [
        "Element added"
      ],
      "url": "/us/dc/council/acts/25-282#\u00a72",
      "doc_mpath": "D.C. Act 25-282|2|",
      "lib_mpath": "DCCouncil/law-rdf|dclaws|25|permanent|pending|",
      "reason": null
    },
    {
      "doc": "D.C. Act 25-282",
      "path": "\u00a73",
      "ptag": "section",
      "cite": "\u00a7 3",
      "statuses": [
        "Element added"
      ],
      "url": "/us/dc/council/acts/25-282#\u00a73",
      "doc_mpath": "D.C. Act 25-282|3|",
      "lib_mpath": "DCCouncil/law-rdf|dclaws|25|permanent|pending|",
      "reason": null
    },
    {
      "doc": "D.C. Act 25-282",
      "path": "\u00a74",
      "ptag": "section",
      "cite": "\u00a7 4",
      "statuses": [
        "Element added"
      ],
      "url": "/us/dc/council/acts/25-282#\u00a74",
      "doc_mpath": "D.C. Act 25-282|4|",
      "lib_mpath": "DCCouncil/law-rdf|dclaws|25|permanent|pending|",
      "reason": null
    },
    {
      "doc": "D.C. Act 25-288",
      "path": "",
      "ptag": "document",
      "cite": "",
      "statuses": [
        "Element added"
      ],
      "url": "/us/dc/council/acts/25-288",
      "doc_mpath": "D.C. Act 25-288|",
      "lib_mpath": "DCCouncil/law-rdf|dclaws|25|temporary|pending|",
      "reason": null
    },
    {
      "doc": "D.C. Act 25-288",
      "path": "\u00a72",
      "ptag": "section",
      "cite": "\u00a7 2",
      "statuses": [
        "Element added"
      ],
      "url": "/us/dc/council/acts/25-288#\u00a72",
      "doc_mpath": "D.C. Act 25-288|2|",
      "lib_mpath": "DCCouncil/law-rdf|dclaws|25|temporary|pending|",
      "reason": null
    },
    {
      "doc": "D.C. Act 25-288",
      "path": "\u00a73",
      "ptag": "section",
      "cite": "\u00a7 3",
      "statuses": [
        "Element added"
      ],
      "url": "/us/dc/council/acts/25-288#\u00a73",
      "doc_mpath": "D.C. Act 25-288|3|",
      "lib_mpath": "DCCouncil/law-rdf|dclaws|25|temporary|pending|",
      "reason": null
    },
    {
      "doc": "D.C. Act 25-288",
      "path": "\u00a74",
      "ptag": "section",
      "cite": "\u00a7 4",
      "statuses": [
        "Element added"
      ],
      "url": "/us/dc/council/acts/25-288#\u00a74",
      "doc_mpath": "D.C. Act 25-288|4|",
      "lib_mpath": "DCCouncil/law-rdf|dclaws|25|temporary|pending|",
      "reason": null
    },
    {
      "doc": "D.C. Act 25-289",
      "path": "",
      "ptag": "document",
      "cite": "",
      "statuses": [
        "Element added"
      ],
      "url": "/us/dc/council/acts/25-289",
      "doc_mpath": "D.C. Act 25-289|",
      "lib_mpath": "DCCouncil/law-rdf|dclaws|25|temporary|pending|",
      "reason": null
    },
    {
      "doc": "D.C. Act 25-289",
      "path": "\u00a72",
      "ptag": "section",
      "cite": "\u00a7 2",
      "statuses": [
        "Element added"
      ],
      "url": "/us/dc/council/acts/25-289#\u00a72",
      "doc_mpath": "D.C. Act 25-289|2|",
      "lib_mpath": "DCCouncil/law-rdf|dclaws|25|temporary|pending|",
      "reason": null
    },
    {
      "doc": "D.C. Act 25-289",
      "path": "\u00a73",
      "ptag": "section",
      "cite": "\u00a7 3",
      "statuses": [
        "Element added"
      ],
      "url": "/us/dc/council/acts/25-289#\u00a73",
      "doc_mpath": "D.C. Act 25-289|3|",
      "lib_mpath": "DCCouncil/law-rdf|dclaws|25|temporary|pending|",
      "reason": null
    },
    {
      "doc": "D.C. Act 25-289",
      "path": "\u00a74",
      "ptag": "section",
      "cite": "\u00a7 4",
      "statuses": [
        "Element added"
      ],
      "url": "/us/dc/council/acts/25-289#\u00a74",
      "doc_mpath": "D.C. Act 25-289|4|",
      "lib_mpath": "DCCouncil/law-rdf|dclaws|25|temporary|pending|",
      "reason": null
    },
    {
      "doc": "D.C. Act 25-289",
      "path": "\u00a7[5]",
      "ptag": "section",
      "cite": "\u00a7 [5]",
      "statuses": [
        "Element added"
      ],
      "url": "/us/dc/council/acts/25-289#\u00a7[5]",
      "doc_mpath": "D.C. Act 25-289|[5]|",
      "lib_mpath": "DCCouncil/law-rdf|dclaws|25|temporary|pending|",
      "reason": null
    },
    {
      "doc": "D.C. Act 25-290",
      "path": "",
      "ptag": "document",
      "cite": "",
      "statuses": [
        "Element added"
      ],
      "url": "/us/dc/council/acts/25-290",
      "doc_mpath": "D.C. Act 25-290|",
      "lib_mpath": "DCCouncil/law-rdf|dclaws|25|temporary|pending|",
      "reason": null
    },
    {
      "doc": "D.C. Act 25-290",
      "path": "\u00a72",
      "ptag": "section",
      "cite": "\u00a7 2",
      "statuses": [
        "Element added"
      ],
      "url": "/us/dc/council/acts/25-290#\u00a72",
      "doc_mpath": "D.C. Act 25-290|2|",
      "lib_mpath": "DCCouncil/law-rdf|dclaws|25|temporary|pending|",
      "reason": null
    },
    {
      "doc": "D.C. Act 25-290",
      "path": "\u00a73",
      "ptag": "section",
      "cite": "\u00a7 3",
      "statuses": [
        "Element added"
      ],
      "url": "/us/dc/council/acts/25-290#\u00a73",
      "doc_mpath": "D.C. Act 25-290|3|",
      "lib_mpath": "DCCouncil/law-rdf|dclaws|25|temporary|pending|",
      "reason": null
    },
    {
      "doc": "D.C. Act 25-290",
      "path": "\u00a74",
      "ptag": "section",
      "cite": "\u00a7 4",
      "statuses": [
        "Element added"
      ],
      "url": "/us/dc/council/acts/25-290#\u00a74",
      "doc_mpath": "D.C. Act 25-290|4|",
      "lib_mpath": "DCCouncil/law-rdf|dclaws|25|temporary|pending|",
      "reason": null
    },
    {
      "doc": "D.C. Act 25-290",
      "path": "\u00a75",
      "ptag": "section",
      "cite": "\u00a7 5",
      "statuses": [
        "Element added"
      ],
      "url": "/us/dc/council/acts/25-290#\u00a75",
      "doc_mpath": "D.C. Act 25-290|5|",
      "lib_mpath": "DCCouncil/law-rdf|dclaws|25|temporary|pending|",
      "reason": null
    },
    {
      "doc": "D.C. Act 25-290",
      "path": "\u00a76",
      "ptag": "section",
      "cite": "\u00a7 6",
      "statuses": [
        "Element added"
      ],
      "url": "/us/dc/council/acts/25-290#\u00a76",
      "doc_mpath": "D.C. Act 25-290|6|",
      "lib_mpath": "DCCouncil/law-rdf|dclaws|25|temporary|pending|",
      "reason": null
    },
    {
      "doc": "D.C. Act 25-290",
      "path": "\u00a77",
      "ptag": "section",
      "cite": "\u00a7 7",
      "statuses": [
        "Element added"
      ],
      "url": "/us/dc/council/acts/25-290#\u00a77",
      "doc_mpath": "D.C. Act 25-290|7|",
      "lib_mpath": "DCCouncil/law-rdf|dclaws|25|temporary|pending|",
      "reason": null
    },
    {
      "doc": "D.C. Act 25-300",
      "path": "",
      "ptag": "document",
      "cite": "",
      "statuses": [
        "Element added"
      ],
      "url": "/us/dc/council/acts/25-300",
      "doc_mpath": "D.C. Act 25-300|",
      "lib_mpath": "DCCouncil/law-rdf|dclaws|25|permanent|pending|",
      "reason": null
    },
    {
      "doc": "D.C. Act 25-300",
      "path": "\u00a72",
      "ptag": "section",
      "cite": "\u00a7 2",
      "statuses": [
        "Element added"
      ],
      "url": "/us/dc/council/acts/25-300#\u00a72",
      "doc_mpath": "D.C. Act 25-300|2|",
      "lib_mpath": "DCCouncil/law-rdf|dclaws|25|permanent|pending|",
      "reason": null
    },
    {
      "doc": "D.C. Act 25-300",
      "path": "\u00a73",
      "ptag": "section",
      "cite": "\u00a7 3",
      "statuses": [
        "Element added"
      ],
      "url": "/us/dc/council/acts/25-300#\u00a73",
      "doc_mpath": "D.C. Act 25-300|3|",
      "lib_mpath": "DCCouncil/law-rdf|dclaws|25|permanent|pending|",
      "reason": null
    },
    {
      "doc": "D.C. Act 25-300",
      "path": "\u00a74",
      "ptag": "section",
      "cite": "\u00a7 4",
      "statuses": [
        "Element added"
      ],
      "url": "/us/dc/council/acts/25-300#\u00a74",
      "doc_mpath": "D.C. Act 25-300|4|",
      "lib_mpath": "DCCouncil/law-rdf|dclaws|25|permanent|pending|",
      "reason": null
    },
    {
      "doc": "D.C. Act 25-301",
      "path": "",
      "ptag": "document",
      "cite": "",
      "statuses": [
        "Element added"
      ],
      "url": "/us/dc/council/acts/25-301",
      "doc_mpath": "D.C. Act 25-301|",
      "lib_mpath": "DCCouncil/law-rdf|dclaws|25|permanent|pending|",
      "reason": null
    },
    {
      "doc": "D.C. Act 25-301",
      "path": "I",
      "ptag": "container",
      "cite": "title I",
      "statuses": [
        "Element added"
      ],
      "url": "/us/dc/council/acts/25-301#/titles/I",
      "doc_mpath": "D.C. Act 25-301|I|",
      "lib_mpath": "DCCouncil/law-rdf|dclaws|25|permanent|pending|",
      "reason": null
    },
    {
      "doc": "D.C. Act 25-301",
      "path": "II",
      "ptag": "container",
      "cite": "title II",
      "statuses": [
        "Element added"
      ],
      "url": "/us/dc/council/acts/25-301#/titles/II",
      "doc_mpath": "D.C. Act 25-301|II|",
      "lib_mpath": "DCCouncil/law-rdf|dclaws|25|permanent|pending|",
      "reason": null
    },
    {
      "doc": "D.C. Act 25-301",
      "path": "III",
      "ptag": "container",
      "cite": "title III",
      "statuses": [
        "Element added"
      ],
      "url": "/us/dc/council/acts/25-301#/titles/III",
      "doc_mpath": "D.C. Act 25-301|III|",
      "lib_mpath": "DCCouncil/law-rdf|dclaws|25|permanent|pending|",
      "reason": null
    },
    {
      "doc": "D.C. Act 25-301",
      "path": "\u00a7101",
      "ptag": "section",
      "cite": "\u00a7 101",
      "statuses": [
        "Element added"
      ],
      "url": "/us/dc/council/acts/25-301#\u00a7101",
      "doc_mpath": "D.C. Act 25-301|I|101|",
      "lib_mpath": "DCCouncil/law-rdf|dclaws|25|permanent|pending|",
      "reason": null
    },
    {
      "doc": "D.C. Act 25-301",
      "path": "\u00a7102",
      "ptag": "section",
      "cite": "\u00a7 102",
      "statuses": [
        "Element added"
      ],
      "url": "/us/dc/council/acts/25-301#\u00a7102",
      "doc_mpath": "D.C. Act 25-301|I|102|",
      "lib_mpath": "DCCouncil/law-rdf|dclaws|25|permanent|pending|",
      "reason": null
    },
    {
      "doc": "D.C. Act 25-301",
      "path": "\u00a7103",
      "ptag": "section",
      "cite": "\u00a7 103",
      "statuses": [
        "Element added"
      ],
      "url": "/us/dc/council/acts/25-301#\u00a7103",
      "doc_mpath": "D.C. Act 25-301|I|103|",
      "lib_mpath": "DCCouncil/law-rdf|dclaws|25|permanent|pending|",
      "reason": null
    },
    {
      "doc": "D.C. Act 25-301",
      "path": "\u00a7104",
      "ptag": "section",
      "cite": "\u00a7 104",
      "statuses": [
        "Element added"
      ],
      "url": "/us/dc/council/acts/25-301#\u00a7104",
      "doc_mpath": "D.C. Act 25-301|I|104|",
      "lib_mpath": "DCCouncil/law-rdf|dclaws|25|permanent|pending|",
      "reason": null
    },
    {
      "doc": "D.C. Act 25-301",
      "path": "\u00a7105",
      "ptag": "section",
      "cite": "\u00a7 105",
      "statuses": [
        "Element added"
      ],
      "url": "/us/dc/council/acts/25-301#\u00a7105",
      "doc_mpath": "D.C. Act 25-301|I|105|",
      "lib_mpath": "DCCouncil/law-rdf|dclaws|25|permanent|pending|",
      "reason": null
    },
    {
      "doc": "D.C. Act 25-301",
      "path": "\u00a7106",
      "ptag": "section",
      "cite": "\u00a7 106",
      "statuses": [
        "Element added"
      ],
      "url": "/us/dc/council/acts/25-301#\u00a7106",
      "doc_mpath": "D.C. Act 25-301|I|106|",
      "lib_mpath": "DCCouncil/law-rdf|dclaws|25|permanent|pending|",
      "reason": null
    },
    {
      "doc": "D.C. Act 25-301",
      "path": "\u00a7107",
      "ptag": "section",
      "cite": "\u00a7 107",
      "statuses": [
        "Element added"
      ],
      "url": "/us/dc/council/acts/25-301#\u00a7107",
      "doc_mpath": "D.C. Act 25-301|I|107|",
      "lib_mpath": "DCCouncil/law-rdf|dclaws|25|permanent|pending|",
      "reason": null
    },
    {
      "doc": "D.C. Act 25-301",
      "path": "\u00a7108",
      "ptag": "section",
      "cite": "\u00a7 108",
      "statuses": [
        "Element added"
      ],
      "url": "/us/dc/council/acts/25-301#\u00a7108",
      "doc_mpath": "D.C. Act 25-301|I|108|",
      "lib_mpath": "DCCouncil/law-rdf|dclaws|25|permanent|pending|",
      "reason": null
    },
    {
      "doc": "D.C. Act 25-301",
      "path": "\u00a7109",
      "ptag": "section",
      "cite": "\u00a7 109",
      "statuses": [
        "Element added"
      ],
      "url": "/us/dc/council/acts/25-301#\u00a7109",
      "doc_mpath": "D.C. Act 25-301|I|109|",
      "lib_mpath": "DCCouncil/law-rdf|dclaws|25|permanent|pending|",
      "reason": null
    },
    {
      "doc": "D.C. Act 25-301",
      "path": "\u00a7110",
      "ptag": "section",
      "cite": "\u00a7 110",
      "statuses": [
        "Element added"
      ],
      "url": "/us/dc/council/acts/25-301#\u00a7110",
      "doc_mpath": "D.C. Act 25-301|I|110|",
      "lib_mpath": "DCCouncil/law-rdf|dclaws|25|permanent|pending|",
      "reason": null
    },
    {
      "doc": "D.C. Act 25-301",
      "path": "\u00a7201",
      "ptag": "section",
      "cite": "\u00a7 201",
      "statuses": [
        "Element added"
      ],
      "url": "/us/dc/council/acts/25-301#\u00a7201",
      "doc_mpath": "D.C. Act 25-301|II|201|",
      "lib_mpath": "DCCouncil/law-rdf|dclaws|25|permanent|pending|",
      "reason": null
    },
    {
      "doc": "D.C. Act 25-301",
      "path": "\u00a7202",
      "ptag": "section",
      "cite": "\u00a7 202",
      "statuses": [
        "Element added"
      ],
      "url": "/us/dc/council/acts/25-301#\u00a7202",
      "doc_mpath": "D.C. Act 25-301|II|202|",
      "lib_mpath": "DCCouncil/law-rdf|dclaws|25|permanent|pending|",
      "reason": null
    },
    {
      "doc": "D.C. Act 25-301",
      "path": "\u00a7301",
      "ptag": "section",
      "cite": "\u00a7 301",
      "statuses": [
        "Element added"
      ],
      "url": "/us/dc/council/acts/25-301#\u00a7301",
      "doc_mpath": "D.C. Act 25-301|III|301|",
      "lib_mpath": "DCCouncil/law-rdf|dclaws|25|permanent|pending|",
      "reason": null
    },
    {
      "doc": "D.C. Act 25-301",
      "path": "\u00a7302",
      "ptag": "section",
      "cite": "\u00a7 302",
      "statuses": [
        "Element added"
      ],
      "url": "/us/dc/council/acts/25-301#\u00a7302",
      "doc_mpath": "D.C. Act 25-301|III|302|",
      "lib_mpath": "DCCouncil/law-rdf|dclaws|25|permanent|pending|",
      "reason": null
    },
    {
      "doc": "D.C. Act 25-301",
      "path": "\u00a7303",
      "ptag": "section",
      "cite": "\u00a7 303",
      "statuses": [
        "Element added"
      ],
      "url": "/us/dc/council/acts/25-301#\u00a7303",
      "doc_mpath": "D.C. Act 25-301|III|303|",
      "lib_mpath": "DCCouncil/law-rdf|dclaws|25|permanent|pending|",
      "reason": null
    },
    {
      "doc": "D.C. Act 25-305",
      "path": "",
      "ptag": "document",
      "cite": "",
      "statuses": [
        "Element added"
      ],
      "url": "/us/dc/council/acts/25-305",
      "doc_mpath": "D.C. Act 25-305|",
      "lib_mpath": "DCCouncil/law-rdf|dclaws|25|emergency|",
      "reason": null
    },
    {
      "doc": "D.C. Act 25-305",
      "path": "\u00a72",
      "ptag": "section",
      "cite": "\u00a7 2",
      "statuses": [
        "Element added"
      ],
      "url": "/us/dc/council/acts/25-305#\u00a72",
      "doc_mpath": "D.C. Act 25-305|2|",
      "lib_mpath": "DCCouncil/law-rdf|dclaws|25|emergency|",
      "reason": null
    },
    {
      "doc": "D.C. Act 25-305",
      "path": "\u00a73",
      "ptag": "section",
      "cite": "\u00a7 3",
      "statuses": [
        "Element added"
      ],
      "url": "/us/dc/council/acts/25-305#\u00a73",
      "doc_mpath": "D.C. Act 25-305|3|",
      "lib_mpath": "DCCouncil/law-rdf|dclaws|25|emergency|",
      "reason": null
    },
    {
      "doc": "D.C. Act 25-305",
      "path": "\u00a74",
      "ptag": "section",
      "cite": "\u00a7 4",
      "statuses": [
        "Element added"
      ],
      "url": "/us/dc/council/acts/25-305#\u00a74",
      "doc_mpath": "D.C. Act 25-305|4|",
      "lib_mpath": "DCCouncil/law-rdf|dclaws|25|emergency|",
      "reason": null
    },
    {
      "doc": "D.C. Act 25-319",
      "path": "",
      "ptag": "document",
      "cite": "",
      "statuses": [
        "Element added"
      ],
      "url": "/us/dc/council/acts/25-319",
      "doc_mpath": "D.C. Act 25-319|",
      "lib_mpath": "DCCouncil/law-rdf|dclaws|25|emergency|",
      "reason": null
    },
    {
      "doc": "D.C. Act 25-319",
      "path": "\u00a72",
      "ptag": "section",
      "cite": "\u00a7 2",
      "statuses": [
        "Element added"
      ],
      "url": "/us/dc/council/acts/25-319#\u00a72",
      "doc_mpath": "D.C. Act 25-319|2|",
      "lib_mpath": "DCCouncil/law-rdf|dclaws|25|emergency|",
      "reason": null
    },
    {
      "doc": "D.C. Act 25-319",
      "path": "\u00a73",
      "ptag": "section",
      "cite": "\u00a7 3",
      "statuses": [
        "Element added"
      ],
      "url": "/us/dc/council/acts/25-319#\u00a73",
      "doc_mpath": "D.C. Act 25-319|3|",
      "lib_mpath": "DCCouncil/law-rdf|dclaws|25|emergency|",
      "reason": null
    },
    {
      "doc": "D.C. Act 25-319",
      "path": "\u00a74",
      "ptag": "section",
      "cite": "\u00a7 4",
      "statuses": [
        "Element added"
      ],
      "url": "/us/dc/council/acts/25-319#\u00a74",
      "doc_mpath": "D.C. Act 25-319|4|",
      "lib_mpath": "DCCouncil/law-rdf|dclaws|25|emergency|",
      "reason": null
    },
    {
      "doc": "D.C. Act 25-319",
      "path": "\u00a75",
      "ptag": "section",
      "cite": "\u00a7 5",
      "statuses": [
        "Element added"
      ],
      "url": "/us/dc/council/acts/25-319#\u00a75",
      "doc_mpath": "D.C. Act 25-319|5|",
      "lib_mpath": "DCCouncil/law-rdf|dclaws|25|emergency|",
      "reason": null
    },
    {
      "doc": "D.C. Act 25-320",
      "path": "",
      "ptag": "document",
      "cite": "",
      "statuses": [
        "Element added"
      ],
      "url": "/us/dc/council/acts/25-320",
      "doc_mpath": "D.C. Act 25-320|",
      "lib_mpath": "DCCouncil/law-rdf|dclaws|25|emergency|",
      "reason": null
    },
    {
      "doc": "D.C. Act 25-320",
      "path": "\u00a72",
      "ptag": "section",
      "cite": "\u00a7 2",
      "statuses": [
        "Element added"
      ],
      "url": "/us/dc/council/acts/25-320#\u00a72",
      "doc_mpath": "D.C. Act 25-320|2|",
      "lib_mpath": "DCCouncil/law-rdf|dclaws|25|emergency|",
      "reason": null
    },
    {
      "doc": "D.C. Act 25-320",
      "path": "\u00a73",
      "ptag": "section",
      "cite": "\u00a7 3",
      "statuses": [
        "Element added"
      ],
      "url": "/us/dc/council/acts/25-320#\u00a73",
      "doc_mpath": "D.C. Act 25-320|3|",
      "lib_mpath": "DCCouncil/law-rdf|dclaws|25|emergency|",
      "reason": null
    },
    {
      "doc": "D.C. Act 25-320",
      "path": "\u00a74",
      "ptag": "section",
      "cite": "\u00a7 4",
      "statuses": [
        "Element added"
      ],
      "url": "/us/dc/council/acts/25-320#\u00a74",
      "doc_mpath": "D.C. Act 25-320|4|",
      "lib_mpath": "DCCouncil/law-rdf|dclaws|25|emergency|",
      "reason": null
    },
    {
      "doc": "D.C. Act 25-321",
      "path": "",
      "ptag": "document",
      "cite": "",
      "statuses": [
        "Element added"
      ],
      "url": "/us/dc/council/acts/25-321",
      "doc_mpath": "D.C. Act 25-321|",
      "lib_mpath": "DCCouncil/law-rdf|dclaws|25|emergency|",
      "reason": null
    },
    {
      "doc": "D.C. Act 25-321",
      "path": "\u00a72",
      "ptag": "section",
      "cite": "\u00a7 2",
      "statuses": [
        "Element added"
      ],
      "url": "/us/dc/council/acts/25-321#\u00a72",
      "doc_mpath": "D.C. Act 25-321|2|",
      "lib_mpath": "DCCouncil/law-rdf|dclaws|25|emergency|",
      "reason": null
    },
    {
      "doc": "D.C. Act 25-321",
      "path": "\u00a73",
      "ptag": "section",
      "cite": "\u00a7 3",
      "statuses": [
        "Element added"
      ],
      "url": "/us/dc/council/acts/25-321#\u00a73",
      "doc_mpath": "D.C. Act 25-321|3|",
      "lib_mpath": "DCCouncil/law-rdf|dclaws|25|emergency|",
      "reason": null
    },
    {
      "doc": "D.C. Act 25-321",
      "path": "\u00a74",
      "ptag": "section",
      "cite": "\u00a7 4",
      "statuses": [
        "Element added"
      ],
      "url": "/us/dc/council/acts/25-321#\u00a74",
      "doc_mpath": "D.C. Act 25-321|4|",
      "lib_mpath": "DCCouncil/law-rdf|dclaws|25|emergency|",
      "reason": null
    },
    {
      "doc": "D.C. Act 25-322",
      "path": "",
      "ptag": "document",
      "cite": "",
      "statuses": [
        "Element added"
      ],
      "url": "/us/dc/council/acts/25-322",
      "doc_mpath": "D.C. Act 25-322|",
      "lib_mpath": "DCCouncil/law-rdf|dclaws|25|permanent|pending|",
      "reason": null
    },
    {
      "doc": "D.C. Act 25-322",
      "path": "\u00a72",
      "ptag": "section",
      "cite": "\u00a7 2",
      "statuses": [
        "Element added"
      ],
      "url": "/us/dc/council/acts/25-322#\u00a72",
      "doc_mpath": "D.C. Act 25-322|2|",
      "lib_mpath": "DCCouncil/law-rdf|dclaws|25|permanent|pending|",
      "reason": null
    },
    {
      "doc": "D.C. Act 25-322",
      "path": "\u00a73",
      "ptag": "section",
      "cite": "\u00a7 3",
      "statuses": [
        "Element added"
      ],
      "url": "/us/dc/council/acts/25-322#\u00a73",
      "doc_mpath": "D.C. Act 25-322|3|",
      "lib_mpath": "DCCouncil/law-rdf|dclaws|25|permanent|pending|",
      "reason": null
    },
    {
      "doc": "D.C. Act 25-322",
      "path": "\u00a74",
      "ptag": "section",
      "cite": "\u00a7 4",
      "statuses": [
        "Element added"
      ],
      "url": "/us/dc/council/acts/25-322#\u00a74",
      "doc_mpath": "D.C. Act 25-322|4|",
      "lib_mpath": "DCCouncil/law-rdf|dclaws|25|permanent|pending|",
      "reason": null
    },
    {
      "doc": "D.C. Code",
      "path": "\u00a710-1604.01",
      "ptag": "section",
      "cite": "\u00a7 10-1604.01",
      "statuses": [
        "Element changed"
      ],
      "url": "/us/dc/council/code/sections/10-1604.01",
      "doc_mpath": "D.C. Code|10|16|IV|10-1604.01|",
      "lib_mpath": "DCCouncil/law-rdf|",
      "reason": null
    },
    {
      "doc": "D.C. Code",
      "path": "\u00a716-2399.01",
      "ptag": "section",
      "cite": "\u00a7 16-2399.01",
      "statuses": [
        "Element changed"
      ],
      "url": "/us/dc/council/code/sections/16-2399.01",
      "doc_mpath": "D.C. Code|16|23|VI|16-2399.01|",
      "lib_mpath": "DCCouncil/law-rdf|",
      "reason": null
    },
    {
      "doc": "D.C. Code",
      "path": "\u00a716-2399.02",
      "ptag": "section",
      "cite": "\u00a7 16-2399.02",
      "statuses": [
        "Element changed"
      ],
      "url": "/us/dc/council/code/sections/16-2399.02",
      "doc_mpath": "D.C. Code|16|23|VI|16-2399.02|",
      "lib_mpath": "DCCouncil/law-rdf|",
      "reason": null
    },
    {
      "doc": "D.C. Code",
      "path": "\u00a716-2399.05",
      "ptag": "section",
      "cite": "\u00a7 16-2399.05",
      "statuses": [
        "Element changed"
      ],
      "url": "/us/dc/council/code/sections/16-2399.05",
      "doc_mpath": "D.C. Code|16|23|VI|16-2399.05|",
      "lib_mpath": "DCCouncil/law-rdf|",
      "reason": null
    },
    {
      "doc": "D.C. Code",
      "path": "\u00a716-2399.06",
      "ptag": "section",
      "cite": "\u00a7 16-2399.06",
      "statuses": [
        "Element changed"
      ],
      "url": "/us/dc/council/code/sections/16-2399.06",
      "doc_mpath": "D.C. Code|16|23|VI|16-2399.06|",
      "lib_mpath": "DCCouncil/law-rdf|",
      "reason": null
    },
    {
      "doc": "D.C. Code",
      "path": "\u00a716-2399.07",
      "ptag": "section",
      "cite": "\u00a7 16-2399.07",
      "statuses": [
        "Element changed"
      ],
      "url": "/us/dc/council/code/sections/16-2399.07",
      "doc_mpath": "D.C. Code|16|23|VI|16-2399.07|",
      "lib_mpath": "DCCouncil/law-rdf|",
      "reason": null
    },
    {
      "doc": "D.C. Code",
      "path": "\u00a728-3871",
      "ptag": "section",
      "cite": "\u00a7 28-3871",
      "statuses": [
        "Element changed"
      ],
      "url": "/us/dc/council/code/sections/28-3871",
      "doc_mpath": "D.C. Code|28|38|IV|28-3871|",
      "lib_mpath": "DCCouncil/law-rdf|",
      "reason": null
    },
    {
      "doc": "D.C. Code",
      "path": "\u00a732-1003",
      "ptag": "section",
      "cite": "\u00a7 32-1003",
      "statuses": [
        "Element changed"
      ],
      "url": "/us/dc/council/code/sections/32-1003",
      "doc_mpath": "D.C. Code|32|10|I|32-1003|",
      "lib_mpath": "DCCouncil/law-rdf|",
      "reason": null
    },
    {
      "doc": "D.C. Code",
      "path": "\u00a738-502.01",
      "ptag": "section",
      "cite": "\u00a7 38-502.01",
      "statuses": [
        "Element changed"
      ],
      "url": "/us/dc/council/code/sections/38-502.01",
      "doc_mpath": "D.C. Code|38|5|38-502.01|",
      "lib_mpath": "DCCouncil/law-rdf|",
      "reason": "Repealed"
    },
    {
      "doc": "D.C. Code",
      "path": "\u00a74-773.05",
      "ptag": "section",
      "cite": "\u00a7 4-773.05",
      "statuses": [
        "Element changed"
      ],
      "url": "/us/dc/council/code/sections/4-773.05",
      "doc_mpath": "D.C. Code|4|7C|4-773.05|",
      "lib_mpath": "DCCouncil/law-rdf|",
      "reason": null
    },
    {
      "doc": "D.C. Code",
      "path": "\u00a742-851.11",
      "ptag": "section",
      "cite": "\u00a7 42-851.11",
      "statuses": [
        "Element changed"
      ],
      "url": "/us/dc/council/code/sections/42-851.11",
      "doc_mpath": "D.C. Code|42|8B|42-851.11|",
      "lib_mpath": "DCCouncil/law-rdf|",
      "reason": null
    },
    {
      "doc": "D.C. Code",
      "path": "\u00a747-2002.06",
      "ptag": "section",
      "cite": "\u00a7 47-2002.06",
      "statuses": [
        "Element changed"
      ],
      "url": "/us/dc/council/code/sections/47-2002.06",
      "doc_mpath": "D.C. Code|47|20|47-2002.06|",
      "lib_mpath": "DCCouncil/law-rdf|",
      "reason": null
    },
    {
      "doc": "D.C. Code",
      "path": "\u00a76-507",
      "ptag": "section",
      "cite": "\u00a7 6-507",
      "statuses": [
        "Element changed"
      ],
      "url": "/us/dc/council/code/sections/6-507",
      "doc_mpath": "D.C. Code|6|5|6-507|",
      "lib_mpath": "DCCouncil/law-rdf|",
      "reason": "Repealed"
    },
    {
      "doc": "D.C. Code",
      "path": "\u00a77-2502.13a",
      "ptag": "section",
      "cite": "\u00a7 7-2502.13a",
      "statuses": [
        "Element added"
      ],
      "url": "/us/dc/council/code/sections/7-2502.13a",
      "doc_mpath": "D.C. Code|7|25|II|7-2502.13a|",
      "lib_mpath": "DCCouncil/law-rdf|",
      "reason": null
    },
    {
      "doc": "D.C. Code",
      "path": "\u00a7[16-2399.09]",
      "ptag": "section",
      "cite": "\u00a7 [16-2399.09]",
      "statuses": [
        "Element changed"
      ],
      "url": "/us/dc/council/code/sections/[16-2399.09]",
      "doc_mpath": "D.C. Code|16|23|VI|[16-2399.09]|",
      "lib_mpath": "DCCouncil/law-rdf|",
      "reason": null
    },
    {
      "doc": "D.C. Law 17-12",
      "path": "\u00a716",
      "ptag": "section",
      "cite": "\u00a7 16",
      "statuses": [
        "Element changed"
      ],
      "url": "/us/dc/council/laws/17-12#\u00a716",
      "doc_mpath": "D.C. Law 17-12|16|",
      "lib_mpath": "DCCouncil/law-rdf|dclaws|17|",
      "reason": null
    },
    {
      "doc": "D.C. Law 17-12",
      "path": "\u00a72",
      "ptag": "section",
      "cite": "\u00a7 2",
      "statuses": [
        "Element changed"
      ],
      "url": "/us/dc/council/laws/17-12#\u00a72",
      "doc_mpath": "D.C. Law 17-12|2|",
      "lib_mpath": "DCCouncil/law-rdf|dclaws|17|",
      "reason": null
    },
    {
      "doc": "D.C. Law 25-64",
      "path": "\u00a74",
      "ptag": "section",
      "cite": "\u00a7 4",
      "statuses": [
        "Element changed"
      ],
      "url": "/us/dc/council/laws/25-64#\u00a74",
      "doc_mpath": "D.C. Law 25-64|4|",
      "lib_mpath": "DCCouncil/law-rdf|dclaws|25|permanent|effective|",
      "reason": null
    },
    {
      "doc": "D.C. Law 25-72",
      "path": "\u00a7105",
      "ptag": "section",
      "cite": "\u00a7 105",
      "statuses": [
        "Element changed"
      ],
      "url": "/us/dc/council/laws/25-72#\u00a7105",
      "doc_mpath": "D.C. Law 25-72|I|105|",
      "lib_mpath": "DCCouncil/law-rdf|dclaws|25|temporary|effective|",
      "reason": null
    }
  ],
  "publication_name": "publication/2021-10-18",
  "codified_date": "2023-12-14"
}