{
  "data": [
    {
      "doc": "9 Anne, ch. 14",
      "path": "\u00a78",
      "ptag": "section",
      "cite": "\u00a7 8",
      "statuses": [
        "Element changed"
      ],
      "url": "/uk/parliament/sessions/9-Anne/chapters/14#\u00a78",
      "doc_mpath": "9 Anne, ch. 14|8|",
      "lib_mpath": "DCCouncil/law-rdf|uk|",
      "reason": null
    },
    {
      "doc": "Stat. 56-2-ch854",
      "path": "\u00a7807",
      "ptag": "section",
      "cite": "\u00a7 807",
      "statuses": [
        "Element changed"
      ],
      "url": "/us/congress/laws/public/56-2-ch854#\u00a7807",
      "doc_mpath": "Stat. 56-2-ch854|807|",
      "lib_mpath": "DCCouncil/law-rdf|fedlaws|56|",
      "reason": null
    },
    {
      "doc": "Stat. 62-2-ch235",
      "path": "\u00a72",
      "ptag": "section",
      "cite": "\u00a7 2",
      "statuses": [
        "Element changed"
      ],
      "url": "/us/congress/laws/public/62-2-ch235#\u00a72",
      "doc_mpath": "Stat. 62-2-ch235|2|",
      "lib_mpath": "DCCouncil/law-rdf|fedlaws|62|",
      "reason": null
    },
    {
      "doc": "D.C. Code",
      "path": "\u00a716-705",
      "ptag": "section",
      "cite": "\u00a7 16-705",
      "statuses": [
        "Element changed"
      ],
      "url": "/us/dc/council/code/sections/16-705",
      "doc_mpath": "D.C. Code|16|7|16-705|",
      "lib_mpath": "DCCouncil/law-rdf|",
      "reason": null
    },
    {
      "doc": "D.C. Code",
      "path": "\u00a722-3152",
      "ptag": "section",
      "cite": "\u00a7 22-3152",
      "statuses": [
        "Element changed"
      ],
      "url": "/us/dc/council/code/sections/22-3152",
      "doc_mpath": "D.C. Code|22|31B|22-3152|",
      "lib_mpath": "DCCouncil/law-rdf|",
      "reason": null
    },
    {
      "doc": "D.C. Code",
      "path": "\u00a722-3312.03",
      "ptag": "section",
      "cite": "\u00a7 22-3312.03",
      "statuses": [
        "Element changed"
      ],
      "url": "/us/dc/council/code/sections/22-3312.03",
      "doc_mpath": "D.C. Code|22|33|22-3312.03|",
      "lib_mpath": "DCCouncil/law-rdf|",
      "reason": null
    },
    {
      "doc": "D.C. Code",
      "path": "\u00a722-401",
      "ptag": "section",
      "cite": "\u00a7 22-401",
      "statuses": [
        "Element changed"
      ],
      "url": "/us/dc/council/code/sections/22-401",
      "doc_mpath": "D.C. Code|22|4|22-401|",
      "lib_mpath": "DCCouncil/law-rdf|",
      "reason": null
    },
    {
      "doc": "D.C. Code",
      "path": "\u00a722-402",
      "ptag": "section",
      "cite": "\u00a7 22-402",
      "statuses": [
        "Element changed"
      ],
      "url": "/us/dc/council/code/sections/22-402",
      "doc_mpath": "D.C. Code|22|4|22-402|",
      "lib_mpath": "DCCouncil/law-rdf|",
      "reason": null
    },
    {
      "doc": "D.C. Code",
      "path": "\u00a722-403",
      "ptag": "section",
      "cite": "\u00a7 22-403",
      "statuses": [
        "Element changed"
      ],
      "url": "/us/dc/council/code/sections/22-403",
      "doc_mpath": "D.C. Code|22|4|22-403|",
      "lib_mpath": "DCCouncil/law-rdf|",
      "reason": null
    },
    {
      "doc": "D.C. Code",
      "path": "\u00a722-404",
      "ptag": "section",
      "cite": "\u00a7 22-404",
      "statuses": [
        "Element changed"
      ],
      "url": "/us/dc/council/code/sections/22-404",
      "doc_mpath": "D.C. Code|22|4|22-404|",
      "lib_mpath": "DCCouncil/law-rdf|",
      "reason": null
    },
    {
      "doc": "D.C. Code",
      "path": "\u00a722-404.01",
      "ptag": "section",
      "cite": "\u00a7 22-404.01",
      "statuses": [
        "Element changed"
      ],
      "url": "/us/dc/council/code/sections/22-404.01",
      "doc_mpath": "D.C. Code|22|4|22-404.01|",
      "lib_mpath": "DCCouncil/law-rdf|",
      "reason": null
    },
    {
      "doc": "D.C. Code",
      "path": "\u00a722-404.02",
      "ptag": "section",
      "cite": "\u00a7 22-404.02",
      "statuses": [
        "Element changed"
      ],
      "url": "/us/dc/council/code/sections/22-404.02",
      "doc_mpath": "D.C. Code|22|4|22-404.02|",
      "lib_mpath": "DCCouncil/law-rdf|",
      "reason": null
    },
    {
      "doc": "D.C. Code",
      "path": "\u00a722-404.03",
      "ptag": "section",
      "cite": "\u00a7 22-404.03",
      "statuses": [
        "Element changed"
      ],
      "url": "/us/dc/council/code/sections/22-404.03",
      "doc_mpath": "D.C. Code|22|4|22-404.03|",
      "lib_mpath": "DCCouncil/law-rdf|",
      "reason": null
    },
    {
      "doc": "D.C. Code",
      "path": "\u00a722-404.04",
      "ptag": "section",
      "cite": "\u00a7 22-404.04",
      "statuses": [
        "Element changed"
      ],
      "url": "/us/dc/council/code/sections/22-404.04",
      "doc_mpath": "D.C. Code|22|4|22-404.04|",
      "lib_mpath": "DCCouncil/law-rdf|",
      "reason": null
    },
    {
      "doc": "D.C. Code",
      "path": "\u00a722-405",
      "ptag": "section",
      "cite": "\u00a7 22-405",
      "statuses": [
        "Element changed"
      ],
      "url": "/us/dc/council/code/sections/22-405",
      "doc_mpath": "D.C. Code|22|4|22-405|",
      "lib_mpath": "DCCouncil/law-rdf|",
      "reason": null
    },
    {
      "doc": "D.C. Code",
      "path": "\u00a722-405.01",
      "ptag": "section",
      "cite": "\u00a7 22-405.01",
      "statuses": [
        "Element added"
      ],
      "url": "/us/dc/council/code/sections/22-405.01",
      "doc_mpath": "D.C. Code|22|4|22-405.01|",
      "lib_mpath": "DCCouncil/law-rdf|",
      "reason": null
    },
    {
      "doc": "D.C. Code",
      "path": "\u00a722-406",
      "ptag": "section",
      "cite": "\u00a7 22-406",
      "statuses": [
        "Element added"
      ],
      "url": "/us/dc/council/code/sections/22-406",
      "doc_mpath": "D.C. Code|22|4|22-406|",
      "lib_mpath": "DCCouncil/law-rdf|",
      "reason": null
    },
    {
      "doc": "D.C. Code",
      "path": "\u00a722-407",
      "ptag": "section",
      "cite": "\u00a7 22-407",
      "statuses": [
        "Element added"
      ],
      "url": "/us/dc/council/code/sections/22-407",
      "doc_mpath": "D.C. Code|22|4|22-407|",
      "lib_mpath": "DCCouncil/law-rdf|",
      "reason": null
    },
    {
      "doc": "D.C. Code",
      "path": "\u00a722-408",
      "ptag": "section",
      "cite": "\u00a7 22-408",
      "statuses": [
        "Element added"
      ],
      "url": "/us/dc/council/code/sections/22-408",
      "doc_mpath": "D.C. Code|22|4|22-408|",
      "lib_mpath": "DCCouncil/law-rdf|",
      "reason": "Repealed"
    },
    {
      "doc": "D.C. Code",
      "path": "\u00a722-431",
      "ptag": "section",
      "cite": "\u00a7 22-431",
      "statuses": [
        "Element removed"
      ],
      "url": "/us/dc/council/code/sections/22-431",
      "doc_mpath": "D.C. Code|22|4|II|22-431|",
      "lib_mpath": "DCCouncil/law-rdf|",
      "reason": null
    },
    {
      "doc": "D.C. Code",
      "path": "\u00a722-432",
      "ptag": "section",
      "cite": "\u00a7 22-432",
      "statuses": [
        "Element removed"
      ],
      "url": "/us/dc/council/code/sections/22-432",
      "doc_mpath": "D.C. Code|22|4|II|22-432|",
      "lib_mpath": "DCCouncil/law-rdf|",
      "reason": null
    },
    {
      "doc": "D.C. Code",
      "path": "\u00a722-451",
      "ptag": "section",
      "cite": "\u00a7 22-451",
      "statuses": [
        "Element removed"
      ],
      "url": "/us/dc/council/code/sections/22-451",
      "doc_mpath": "D.C. Code|22|4|III|22-451|",
      "lib_mpath": "DCCouncil/law-rdf|",
      "reason": null
    },
    {
      "doc": "D.C. Code",
      "path": "\u00a722-471",
      "ptag": "section",
      "cite": "\u00a7 22-471",
      "statuses": [
        "Element removed"
      ],
      "url": "/us/dc/council/code/sections/22-471",
      "doc_mpath": "D.C. Code|22|4|IV|22-471|",
      "lib_mpath": "DCCouncil/law-rdf|",
      "reason": "Repealed"
    },
    {
      "doc": "D.C. Code",
      "path": "\u00a723-524",
      "ptag": "section",
      "cite": "\u00a7 23-524",
      "statuses": [
        "Element changed"
      ],
      "url": "/us/dc/council/code/sections/23-524",
      "doc_mpath": "D.C. Code|23|5|II|23-524|",
      "lib_mpath": "DCCouncil/law-rdf|",
      "reason": null
    },
    {
      "doc": "D.C. Code",
      "path": "\u00a724-112",
      "ptag": "section",
      "cite": "\u00a7 24-112",
      "statuses": [
        "Element changed"
      ],
      "url": "/us/dc/council/code/sections/24-112",
      "doc_mpath": "D.C. Code|24|1|II|24-112|",
      "lib_mpath": "DCCouncil/law-rdf|",
      "reason": null
    },
    {
      "doc": "D.C. Code",
      "path": "\u00a724-261.03",
      "ptag": "section",
      "cite": "\u00a7 24-261.03",
      "statuses": [
        "Element changed"
      ],
      "url": "/us/dc/council/code/sections/24-261.03",
      "doc_mpath": "D.C. Code|24|2|VII|24-261.03|",
      "lib_mpath": "DCCouncil/law-rdf|",
      "reason": null
    },
    {
      "doc": "D.C. Code",
      "path": "\u00a724-403",
      "ptag": "section",
      "cite": "\u00a7 24-403",
      "statuses": [
        "Element changed"
      ],
      "url": "/us/dc/council/code/sections/24-403",
      "doc_mpath": "D.C. Code|24|4|I|24-403|",
      "lib_mpath": "DCCouncil/law-rdf|",
      "reason": null
    },
    {
      "doc": "D.C. Code",
      "path": "\u00a724-403.01",
      "ptag": "section",
      "cite": "\u00a7 24-403.01",
      "statuses": [
        "Element changed"
      ],
      "url": "/us/dc/council/code/sections/24-403.01",
      "doc_mpath": "D.C. Code|24|4|I|24-403.01|",
      "lib_mpath": "DCCouncil/law-rdf|",
      "reason": null
    },
    {
      "doc": "D.C. Code",
      "path": "\u00a73-1201.02",
      "ptag": "section",
      "cite": "\u00a7 3-1201.02",
      "statuses": [
        "Element changed"
      ],
      "url": "/us/dc/council/code/sections/3-1201.02",
      "doc_mpath": "D.C. Code|3|12|I|3-1201.02|",
      "lib_mpath": "DCCouncil/law-rdf|",
      "reason": null
    },
    {
      "doc": "D.C. Code",
      "path": "\u00a73-1201.05",
      "ptag": "section",
      "cite": "\u00a7 3-1201.05",
      "statuses": [
        "Element changed"
      ],
      "url": "/us/dc/council/code/sections/3-1201.05",
      "doc_mpath": "D.C. Code|3|12|I|3-1201.05|",
      "lib_mpath": "DCCouncil/law-rdf|",
      "reason": null
    },
    {
      "doc": "D.C. Code",
      "path": "\u00a73-1202.03",
      "ptag": "section",
      "cite": "\u00a7 3-1202.03",
      "statuses": [
        "Element changed"
      ],
      "url": "/us/dc/council/code/sections/3-1202.03",
      "doc_mpath": "D.C. Code|3|12|II|3-1202.03|",
      "lib_mpath": "DCCouncil/law-rdf|",
      "reason": null
    },
    {
      "doc": "D.C. Code",
      "path": "\u00a73-1202.08",
      "ptag": "section",
      "cite": "\u00a7 3-1202.08",
      "statuses": [
        "Element changed"
      ],
      "url": "/us/dc/council/code/sections/3-1202.08",
      "doc_mpath": "D.C. Code|3|12|II|3-1202.08|",
      "lib_mpath": "DCCouncil/law-rdf|",
      "reason": null
    },
    {
      "doc": "D.C. Code",
      "path": "\u00a73-1202.12",
      "ptag": "section",
      "cite": "\u00a7 3-1202.12",
      "statuses": [
        "Element changed"
      ],
      "url": "/us/dc/council/code/sections/3-1202.12",
      "doc_mpath": "D.C. Code|3|12|II|3-1202.12|",
      "lib_mpath": "DCCouncil/law-rdf|",
      "reason": null
    },
    {
      "doc": "D.C. Code",
      "path": "\u00a73-1202.18",
      "ptag": "section",
      "cite": "\u00a7 3-1202.18",
      "statuses": [
        "Element changed"
      ],
      "url": "/us/dc/council/code/sections/3-1202.18",
      "doc_mpath": "D.C. Code|3|12|II|3-1202.18|",
      "lib_mpath": "DCCouncil/law-rdf|",
      "reason": null
    },
    {
      "doc": "D.C. Code",
      "path": "\u00a73-1204.08",
      "ptag": "section",
      "cite": "\u00a7 3-1204.08",
      "statuses": [
        "Element changed"
      ],
      "url": "/us/dc/council/code/sections/3-1204.08",
      "doc_mpath": "D.C. Code|3|12|IV|3-1204.08|",
      "lib_mpath": "DCCouncil/law-rdf|",
      "reason": null
    },
    {
      "doc": "D.C. Code",
      "path": "\u00a73-1204.13",
      "ptag": "section",
      "cite": "\u00a7 3-1204.13",
      "statuses": [
        "Element changed"
      ],
      "url": "/us/dc/council/code/sections/3-1204.13",
      "doc_mpath": "D.C. Code|3|12|IV|3-1204.13|",
      "lib_mpath": "DCCouncil/law-rdf|",
      "reason": null
    },
    {
      "doc": "D.C. Code",
      "path": "\u00a73-1205.03",
      "ptag": "section",
      "cite": "\u00a7 3-1205.03",
      "statuses": [
        "Element changed"
      ],
      "url": "/us/dc/council/code/sections/3-1205.03",
      "doc_mpath": "D.C. Code|3|12|V|3-1205.03|",
      "lib_mpath": "DCCouncil/law-rdf|",
      "reason": null
    },
    {
      "doc": "D.C. Code",
      "path": "\u00a73-1206.09",
      "ptag": "section",
      "cite": "\u00a7 3-1206.09",
      "statuses": [
        "Element changed"
      ],
      "url": "/us/dc/council/code/sections/3-1206.09",
      "doc_mpath": "D.C. Code|3|12|VI|3-1206.09|",
      "lib_mpath": "DCCouncil/law-rdf|",
      "reason": null
    },
    {
      "doc": "D.C. Code",
      "path": "\u00a73-1207.10",
      "ptag": "section",
      "cite": "\u00a7 3-1207.10",
      "statuses": [
        "Element changed"
      ],
      "url": "/us/dc/council/code/sections/3-1207.10",
      "doc_mpath": "D.C. Code|3|12|VII-A|3-1207.10|",
      "lib_mpath": "DCCouncil/law-rdf|",
      "reason": null
    },
    {
      "doc": "D.C. Code",
      "path": "\u00a73-1207.71",
      "ptag": "section",
      "cite": "\u00a7 3-1207.71",
      "statuses": [
        "Element changed"
      ],
      "url": "/us/dc/council/code/sections/3-1207.71",
      "doc_mpath": "D.C. Code|3|12|VII-G|3-1207.71|",
      "lib_mpath": "DCCouncil/law-rdf|",
      "reason": null
    },
    {
      "doc": "D.C. Code",
      "path": "\u00a73-1208.76",
      "ptag": "section",
      "cite": "\u00a7 3-1208.76",
      "statuses": [
        "Element changed"
      ],
      "url": "/us/dc/council/code/sections/3-1208.76",
      "doc_mpath": "D.C. Code|3|12|VIII-F|3-1208.76|",
      "lib_mpath": "DCCouncil/law-rdf|",
      "reason": null
    },
    {
      "doc": "D.C. Code",
      "path": "\u00a73-1208.81",
      "ptag": "section",
      "cite": "\u00a7 3-1208.81",
      "statuses": [
        "Element changed"
      ],
      "url": "/us/dc/council/code/sections/3-1208.81",
      "doc_mpath": "D.C. Code|3|12|VIII-G|3-1208.81|",
      "lib_mpath": "DCCouncil/law-rdf|",
      "reason": null
    },
    {
      "doc": "D.C. Code",
      "path": "\u00a74-501",
      "ptag": "section",
      "cite": "\u00a7 4-501",
      "statuses": [
        "Element changed"
      ],
      "url": "/us/dc/council/code/sections/4-501",
      "doc_mpath": "D.C. Code|4|5|I|4-501|",
      "lib_mpath": "DCCouncil/law-rdf|",
      "reason": null
    },
    {
      "doc": "D.C. Code",
      "path": "\u00a742-3541.02",
      "ptag": "section",
      "cite": "\u00a7 42-3541.02",
      "statuses": [
        "Element changed"
      ],
      "url": "/us/dc/council/code/sections/42-3541.02",
      "doc_mpath": "D.C. Code|42|35B|42-3541.02|",
      "lib_mpath": "DCCouncil/law-rdf|",
      "reason": null
    },
    {
      "doc": "D.C. Code",
      "path": "\u00a75-132.21",
      "ptag": "section",
      "cite": "\u00a7 5-132.21",
      "statuses": [
        "Element changed"
      ],
      "url": "/us/dc/council/code/sections/5-132.21",
      "doc_mpath": "D.C. Code|5|1|XVI-B|5-132.21|",
      "lib_mpath": "DCCouncil/law-rdf|",
      "reason": null
    },
    {
      "doc": "D.C. Code",
      "path": "\u00a77-2510.07c",
      "ptag": "section",
      "cite": "\u00a7 7-2510.07c",
      "statuses": [
        "Element changed"
      ],
      "url": "/us/dc/council/code/sections/7-2510.07c",
      "doc_mpath": "D.C. Code|7|25|X|7-2510.07c|",
      "lib_mpath": "DCCouncil/law-rdf|",
      "reason": null
    },
    {
      "doc": "D.C. Code",
      "path": "22|4|I",
      "ptag": "container",
      "cite": "subchapter I of Chapter 4 of Title 22",
      "statuses": [
        "Element removed"
      ],
      "url": "/us/dc/council/code/titles/22/chapters/4/subchapters/I",
      "doc_mpath": "D.C. Code|22|4|I|",
      "lib_mpath": "DCCouncil/law-rdf|",
      "reason": null
    },
    {
      "doc": "D.C. Law 21-125",
      "path": "\u00a7206",
      "ptag": "section",
      "cite": "\u00a7 206",
      "statuses": [
        "Element changed"
      ],
      "url": "/us/dc/council/laws/21-125#\u00a7206",
      "doc_mpath": "D.C. Law 21-125|II|D|206|",
      "lib_mpath": "DCCouncil/law-rdf|dclaws|21|permanent|",
      "reason": null
    },
    {
      "doc": "D.C. Law 21-259",
      "path": "\u00a73",
      "ptag": "section",
      "cite": "\u00a7 3",
      "statuses": [
        "Element changed"
      ],
      "url": "/us/dc/council/laws/21-259#\u00a73",
      "doc_mpath": "D.C. Law 21-259|3|",
      "lib_mpath": "DCCouncil/law-rdf|dclaws|21|permanent|",
      "reason": null
    },
    {
      "doc": "D.C. Law 23-274",
      "path": "\u00a7102",
      "ptag": "section",
      "cite": "\u00a7 102",
      "statuses": [
        "Element changed"
      ],
      "url": "/us/dc/council/laws/23-274#\u00a7102",
      "doc_mpath": "D.C. Law 23-274|I|102|",
      "lib_mpath": "DCCouncil/law-rdf|dclaws|23|permanent|",
      "reason": null
    },
    {
      "doc": "D.C. Law 24-345",
      "path": "\u00a7113",
      "ptag": "section",
      "cite": "\u00a7 113",
      "statuses": [
        "Element changed"
      ],
      "url": "/us/dc/council/laws/24-345#\u00a7113",
      "doc_mpath": "D.C. Law 24-345|I|I|113|",
      "lib_mpath": "DCCouncil/law-rdf|dclaws|24|permanent|",
      "reason": null
    },
    {
      "doc": "D.C. Law 25-175",
      "path": "\u00a720",
      "ptag": "section",
      "cite": "\u00a7 20",
      "statuses": [
        "Element changed"
      ],
      "url": "/us/dc/council/laws/25-175#\u00a720",
      "doc_mpath": "D.C. Law 25-175|20|",
      "lib_mpath": "DCCouncil/law-rdf|dclaws|25|permanent|effective|",
      "reason": null
    },
    {
      "doc": "D.C. Law 25-175",
      "path": "\u00a724",
      "ptag": "section",
      "cite": "\u00a7 24",
      "statuses": [
        "Element changed"
      ],
      "url": "/us/dc/council/laws/25-175#\u00a724",
      "doc_mpath": "D.C. Law 25-175|24|",
      "lib_mpath": "DCCouncil/law-rdf|dclaws|25|permanent|effective|",
      "reason": null
    },
    {
      "doc": "D.C. Law 25-191",
      "path": "\u00a7101",
      "ptag": "section",
      "cite": "\u00a7 101",
      "statuses": [
        "Element changed"
      ],
      "url": "/us/dc/council/laws/25-191#\u00a7101",
      "doc_mpath": "D.C. Law 25-191|I|101|",
      "lib_mpath": "DCCouncil/law-rdf|dclaws|25|permanent|effective|",
      "reason": null
    }
  ],
  "publication_name": "publication/2021-10-18",
  "codified_date": "2024-08-20"
}